docent/__init__.py
docent/py.typed
docent/trace.py
docent/trace_temp.py
docent/_llm_util/__init__.py
docent/_llm_util/llm_cache.py
docent/_llm_util/llm_svc.py
docent/_llm_util/model_registry.py
docent/_llm_util/data_models/__init__.py
docent/_llm_util/data_models/exceptions.py
docent/_llm_util/data_models/llm_output.py
docent/_llm_util/providers/__init__.py
docent/_llm_util/providers/anthropic.py
docent/_llm_util/providers/common.py
docent/_llm_util/providers/google.py
docent/_llm_util/providers/openai.py
docent/_llm_util/providers/openrouter.py
docent/_llm_util/providers/preference_types.py
docent/_llm_util/providers/provider_registry.py
docent/_log_util/__init__.py
docent/_log_util/logger.py
docent/data_models/__init__.py
docent/data_models/_tiktoken_util.py
docent/data_models/agent_run.py
docent/data_models/citation.py
docent/data_models/collection.py
docent/data_models/formatted_objects.py
docent/data_models/judge.py
docent/data_models/metadata_util.py
docent/data_models/regex.py
docent/data_models/transcript.py
docent/data_models/util.py
docent/data_models/chat/__init__.py
docent/data_models/chat/content.py
docent/data_models/chat/message.py
docent/data_models/chat/tool.py
docent/judges/__init__.py
docent/judges/analysis.py
docent/judges/impl.py
docent/judges/runner.py
docent/judges/stats.py
docent/judges/types.py
docent/judges/util/forgiving_json.py
docent/judges/util/meta_schema.json
docent/judges/util/meta_schema.py
docent/judges/util/parse_output.py
docent/judges/util/voting.py
docent/loaders/load_inspect.py
docent/samples/__init__.py
docent/samples/load.py
docent/samples/log.eval
docent/samples/tb_airline.json
docent/sdk/__init__.py
docent/sdk/agent_run_writer.py
docent/sdk/client.py
docent/sdk/llm_context.py
docent_python-0.1.38a0.dist-info/METADATA
docent_python-0.1.38a0.dist-info/WHEEL
docent_python-0.1.38a0.dist-info/licenses/LICENSE.md
docent_python-0.1.38a0.dist-info/RECORD
