Metadata-Version: 2.4
Name: docent-python
Version: 0.1.38a0
Summary: Docent SDK
Project-URL: Homepage, https://github.com/TransluceAI/docent
Project-URL: Issues, https://github.com/TransluceAI/docent/issues
Project-URL: Docs, https://transluce-docent.readthedocs-hosted.com/en/latest
Author-email: Transluce <info@transluce.org>
License-Expression: Apache-2.0
License-File: LICENSE.md
Requires-Python: >=3.11
Requires-Dist: anthropic>=0.47.0
Requires-Dist: backoff>=2.2.1
Requires-Dist: google-genai>=1.16.1
Requires-Dist: inspect-ai>=0.3.132
Requires-Dist: jsonschema>=4.24.0
Requires-Dist: openai>=1.68.0
Requires-Dist: opentelemetry-api>=1.34.1
Requires-Dist: opentelemetry-exporter-otlp-proto-grpc>=1.34.1
Requires-Dist: opentelemetry-exporter-otlp-proto-http>=1.34.1
Requires-Dist: opentelemetry-instrumentation-anthropic>=0.40.14
Requires-Dist: opentelemetry-instrumentation-bedrock>=0.40.14
Requires-Dist: opentelemetry-instrumentation-google-generativeai>=0.40.14
Requires-Dist: opentelemetry-instrumentation-langchain>=0.40.14
Requires-Dist: opentelemetry-instrumentation-openai>=0.40.14
Requires-Dist: opentelemetry-instrumentation-threading>=0.55b1
Requires-Dist: opentelemetry-sdk>=1.34.1
Requires-Dist: orjson>=3.11.3
Requires-Dist: pandas>=2.3.3
Requires-Dist: pydantic>=2.11.7
Requires-Dist: pyyaml>=6.0.2
Requires-Dist: tiktoken>=0.7.0
Requires-Dist: tqdm>=4.67.1
